LICENSE
netlookup/__init__.py
netlookup/base.py
netlookup/bin/__init__.py
netlookup/bin/commands/__init__.py
netlookup/bin/commands/base.py
netlookup/bin/commands/info.py
netlookup/bin/commands/prefixes.py
netlookup/bin/commands/split.py
netlookup/bin/commands/substract.py
netlookup/bin/netlookup.py
netlookup/constants.py
netlookup/encoders.py
netlookup/exceptions.py
netlookup/network.py
netlookup/network_sets/__init__.py
netlookup/network_sets/aws.py
netlookup/network_sets/base.py
netlookup/network_sets/cloudflare.py
netlookup/network_sets/constants.py
netlookup/network_sets/google.py
netlookup/prefixes.py
netlookup/protocols.py
netlookup/services.py
netlookup-2.1.0.dist-info/LICENSE
netlookup-2.1.0.dist-info/METADATA
netlookup-2.1.0.dist-info/WHEEL
netlookup-2.1.0.dist-info/entry_points.txt
netlookup-2.1.0.dist-info/RECORD
