Metadata-Version: 2.1
Name: netlookup
Version: 2.1.0
Summary: Python tool to look up information about networks
Home-page: https://github.com/hile/netlookup
License: BSD-3-Clause
Author: Ilkka Tuohela
Author-email: hile@iki.fi
Requires-Python: >=3.9,<4.0
Classifier: Environment :: Console
Classifier: License :: OSI Approved :: BSD License
Classifier: Operating System :: MacOS
Classifier: Operating System :: POSIX
Classifier: Operating System :: Unix
Classifier: Programming Language :: Python :: 3
Classifier: Programming Language :: Python :: 3.9
Classifier: Programming Language :: Python :: 3.10
Classifier: Programming Language :: Python :: 3.11
Classifier: Programming Language :: Python :: 3.12
Classifier: Topic :: Utilities
Requires-Dist: cli-toolkit (>=2,<3)
Requires-Dist: dnspython (>=2,<3)
Requires-Dist: netaddr (>=0.8,<0.9)
Requires-Dist: requests (>=2,<3)
